<?xml version="1.0" encoding="Windows-1252"?>
<!DOCTYPE POWERMART SYSTEM "powrmart.dtd">
<POWERMART CREATION_DATE="03/24/2024 11:36:25" REPOSITORY_VERSION="187.96">
<REPOSITORY NAME="RepSvc" VERSION="187" CODEPAGE="MS1252" DATABASETYPE="Oracle">
<FOLDER NAME="NEW_UAS" GROUP="" OWNER="Administrator" SHARED="NOTSHARED" DESCRIPTION="" PERMISSIONS="rwx---r--" UUID="3b3a3d56-99c2-4570-97a7-ed989086220b">
    <SOURCE BUSINESSNAME ="" DATABASETYPE ="Flat File" DBDNAME ="FlatFile" DESCRIPTION ="" NAME ="CDW_UAS_COURSE" OBJECTVERSION ="1" OWNERNAME ="" VERSIONNUMBER ="1">
        <FLATFILE CODEPAGE ="MS1252" CONSECDELIMITERSASONE ="NO" DELIMITED ="YES" DELIMITERS ="," ESCAPE_CHARACTER ="" KEEPESCAPECHAR ="NO" LINESEQUENTIAL ="NO" MULTIDELIMITERSASAND ="NO" NULLCHARTYPE ="ASCII" NULL_CHARACTER ="*" PADBYTES ="1" QUOTE_CHARACTER ="NONE" REPEATABLE ="NO" ROWDELIMITER ="0" SHIFTSENSITIVEDATA ="NO" SKIPROWS ="1" STRIPTRAILINGBLANKS ="NO"/>
        <TABLEATTRIBUTE NAME ="Base Table Name" VALUE =""/>
        <TABLEATTRIBUTE NAME ="Search Specification" VALUE =""/>
        <TABLEATTRIBUTE NAME ="Sort Specification" VALUE =""/>
        <TABLEATTRIBUTE NAME ="Datetime Format" VALUE ="A  19 mm/dd/yyyy hh24:mi:ss"/>
        <TABLEATTRIBUTE NAME ="Thousand Separator" VALUE ="None"/>
        <TABLEATTRIBUTE NAME ="Decimal Separator" VALUE ="."/>
        <TABLEATTRIBUTE NAME ="Add Currently Processed Flat File Name Port" VALUE ="NO"/>
        <TABLEATTRIBUTE NAME ="Source TimeStamp" VALUE =""/>
        <SOURCEFIELD BUSINESSNAME ="" DATATYPE ="number" DESCRIPTION ="" FIELDNUMBER ="1" FIELDPROPERTY ="0" FIELDTYPE ="ELEMITEM" HIDDEN ="NO" KEYTYPE ="NOT A KEY" LENGTH ="10" LEVEL ="0" NAME ="COURSE_CODE" NULLABLE ="NULL" OCCURS ="0" OFFSET ="0" PHYSICALLENGTH ="10" PHYSICALOFFSET ="0" PICTURETEXT ="" PRECISION ="10" SCALE ="10" USAGE_FLAGS =""/>
        <SOURCEFIELD BUSINESSNAME ="" DATATYPE ="string" DESCRIPTION ="" FIELDNUMBER ="2" FIELDPROPERTY ="0" FIELDTYPE ="ELEMITEM" HIDDEN ="NO" KEYTYPE ="NOT A KEY" LENGTH ="30" LEVEL ="0" NAME ="COURSE_NAME" NULLABLE ="NULL" OCCURS ="0" OFFSET ="10" PHYSICALLENGTH ="30" PHYSICALOFFSET ="10" PICTURETEXT ="" PRECISION ="30" SCALE ="0" USAGE_FLAGS =""/>
        <SOURCEFIELD BUSINESSNAME ="" DATATYPE ="string" DESCRIPTION ="" FIELDNUMBER ="3" FIELDPROPERTY ="0" FIELDTYPE ="ELEMITEM" HIDDEN ="NO" KEYTYPE ="NOT A KEY" LENGTH ="9" LEVEL ="0" NAME ="DEPARTMENT_NO" NULLABLE ="NULL" OCCURS ="0" OFFSET ="40" PHYSICALLENGTH ="9" PHYSICALOFFSET ="40" PICTURETEXT ="" PRECISION ="9" SCALE ="0" USAGE_FLAGS =""/>
        <SOURCEFIELD BUSINESSNAME ="" DATATYPE ="string" DESCRIPTION ="" FIELDNUMBER ="4" FIELDPROPERTY ="0" FIELDTYPE ="ELEMITEM" HIDDEN ="NO" KEYTYPE ="NOT A KEY" LENGTH ="9" LEVEL ="0" NAME ="MARK_REQ" NULLABLE ="NULL" OCCURS ="0" OFFSET ="49" PHYSICALLENGTH ="9" PHYSICALOFFSET ="49" PICTURETEXT ="" PRECISION ="9" SCALE ="0" USAGE_FLAGS =""/>
    </SOURCE>
    <TARGET BUSINESSNAME ="" CONSTRAINT ="" DATABASETYPE ="Oracle" DESCRIPTION ="" NAME ="CDW_UAS_D_DEPARTMENT" OBJECTVERSION ="1" TABLEOPTIONS ="" VERSIONNUMBER ="1">
        <TARGETFIELD BUSINESSNAME ="" DATATYPE ="number(p,s)" DESCRIPTION ="" FIELDNUMBER ="1" KEYTYPE ="PRIMARY KEY" NAME ="DEPARTMENT_ID" NULLABLE ="NOTNULL" PICTURETEXT ="" PRECISION ="10" SCALE ="0"/>
        <TARGETFIELD BUSINESSNAME ="" DATATYPE ="varchar2" DESCRIPTION ="" FIELDNUMBER ="2" KEYTYPE ="NOT A KEY" NAME ="DEPARTMENT_NAME" NULLABLE ="NOTNULL" PICTURETEXT ="" PRECISION ="50" SCALE ="0"/>
        <TARGETFIELD BUSINESSNAME ="" DATATYPE ="number(p,s)" DESCRIPTION ="" FIELDNUMBER ="3" KEYTYPE ="NOT A KEY" NAME ="DEPARTMENT_NO" NULLABLE ="NOTNULL" PICTURETEXT ="" PRECISION ="9" SCALE ="0"/>
        <TARGETFIELD BUSINESSNAME ="" DATATYPE ="varchar2" DESCRIPTION ="" FIELDNUMBER ="4" KEYTYPE ="NOT A KEY" NAME ="DEPARTMENT_PHONE" NULLABLE ="NOTNULL" PICTURETEXT ="" PRECISION ="12" SCALE ="0"/>
        <TARGETFIELD BUSINESSNAME ="" DATATYPE ="varchar2" DESCRIPTION ="" FIELDNUMBER ="5" KEYTYPE ="NOT A KEY" NAME ="DEPARTMENT_HEAD" NULLABLE ="NOTNULL" PICTURETEXT ="" PRECISION ="30" SCALE ="0"/>
    </TARGET>
    <TARGET BUSINESSNAME ="" CONSTRAINT ="" DATABASETYPE ="Oracle" DESCRIPTION ="" NAME ="CDW_SAPP_D_COURSE" OBJECTVERSION ="1" TABLEOPTIONS ="" VERSIONNUMBER ="1">
        <TARGETFIELD BUSINESSNAME ="" DATATYPE ="number(p,s)" DESCRIPTION ="" FIELDNUMBER ="1" KEYTYPE ="PRIMARY KEY" NAME ="COURSE_CODE" NULLABLE ="NOTNULL" PICTURETEXT ="" PRECISION ="10" SCALE ="0"/>
        <TARGETFIELD BUSINESSNAME ="" DATATYPE ="nvarchar2" DESCRIPTION ="" FIELDNUMBER ="2" KEYTYPE ="NOT A KEY" NAME ="COURSE_NAME" NULLABLE ="NOTNULL" PICTURETEXT ="" PRECISION ="30" SCALE ="0"/>
        <TARGETFIELD BUSINESSNAME ="" DATATYPE ="number(p,s)" DESCRIPTION ="" FIELDNUMBER ="3" KEYTYPE ="FOREIGN KEY" NAME ="DEPARTMENT_ID" NULLABLE ="NOTNULL" PICTURETEXT ="" PRECISION ="10" REFERENCEDFIELD ="DEPARTMENT_ID" REFERENCEDTABLE ="CDW_UAS_D_DEPARTMENT" SCALE ="0"/>
        <TARGETFIELD BUSINESSNAME ="" DATATYPE ="nvarchar2" DESCRIPTION ="" FIELDNUMBER ="4" KEYTYPE ="NOT A KEY" NAME ="MARK_REQ" NULLABLE ="NOTNULL" PICTURETEXT ="" PRECISION ="9" SCALE ="0"/>
    </TARGET>
    <MAPPING DESCRIPTION ="" ISVALID ="YES" NAME ="M_UAS_COURSE" OBJECTVERSION ="1" VERSIONNUMBER ="1">
        <TRANSFORMATION DESCRIPTION ="" NAME ="RTR_U_I" OBJECTVERSION ="1" REUSABLE ="NO" TYPE ="Router" VERSIONNUMBER ="1">
            <GROUP DESCRIPTION ="" NAME ="INPUT" ORDER ="1" TYPE ="INPUT"/>
            <GROUP DESCRIPTION ="" EXPRESSION ="NewLookupRow=1 OR NewLookupRow=2" NAME ="UPD_INS" ORDER ="2" TYPE ="OUTPUT"/>
            <GROUP DESCRIPTION ="Path for the data when none of the group conditions are satisfied." NAME ="DEFAULT1" ORDER ="3" TYPE ="OUTPUT/DEFAULT"/>
            <TRANSFORMFIELD DATATYPE ="integer" DEFAULTVALUE ="" DESCRIPTION ="Default port for Dynamic Lookup" GROUP ="INPUT" NAME ="NewLookupRow" PICTURETEXT ="" PORTTYPE ="INPUT" PRECISION ="10" SCALE ="0"/>
            <TRANSFORMFIELD DATATYPE ="decimal" DEFAULTVALUE ="" DESCRIPTION ="" GROUP ="INPUT" NAME ="COURSE_CODE" PICTURETEXT ="" PORTTYPE ="INPUT" PRECISION ="10" SCALE ="0"/>
            <TRANSFORMFIELD DATATYPE ="string" DEFAULTVALUE ="" DESCRIPTION ="" GROUP ="INPUT" NAME ="COURSE_NAME" PICTURETEXT ="" PORTTYPE ="INPUT" PRECISION ="30" SCALE ="0"/>
            <TRANSFORMFIELD DATATYPE ="decimal" DEFAULTVALUE ="" DESCRIPTION ="" GROUP ="INPUT" NAME ="DEPARTMENT_ID" PICTURETEXT ="" PORTTYPE ="INPUT" PRECISION ="10" SCALE ="0"/>
            <TRANSFORMFIELD DATATYPE ="string" DEFAULTVALUE ="" DESCRIPTION ="" GROUP ="INPUT" NAME ="MARK_REQ" PICTURETEXT ="" PORTTYPE ="INPUT" PRECISION ="9" SCALE ="0"/>
            <TRANSFORMFIELD DATATYPE ="integer" DEFAULTVALUE ="" DESCRIPTION ="Default port for Dynamic Lookup" GROUP ="UPD_INS" NAME ="NewLookupRow1" PICTURETEXT ="" PORTTYPE ="OUTPUT" PRECISION ="10" REF_FIELD ="NewLookupRow" SCALE ="0"/>
            <TRANSFORMFIELD DATATYPE ="decimal" DEFAULTVALUE ="" DESCRIPTION ="" GROUP ="UPD_INS" NAME ="COURSE_CODE1" PICTURETEXT ="" PORTTYPE ="OUTPUT" PRECISION ="10" REF_FIELD ="COURSE_CODE" SCALE ="0"/>
            <TRANSFORMFIELD DATATYPE ="string" DEFAULTVALUE ="" DESCRIPTION ="" GROUP ="UPD_INS" NAME ="COURSE_NAME1" PICTURETEXT ="" PORTTYPE ="OUTPUT" PRECISION ="30" REF_FIELD ="COURSE_NAME" SCALE ="0"/>
            <TRANSFORMFIELD DATATYPE ="decimal" DEFAULTVALUE ="" DESCRIPTION ="" GROUP ="UPD_INS" NAME ="DEPARTMENT_ID1" PICTURETEXT ="" PORTTYPE ="OUTPUT" PRECISION ="10" REF_FIELD ="DEPARTMENT_ID" SCALE ="0"/>
            <TRANSFORMFIELD DATATYPE ="string" DEFAULTVALUE ="" DESCRIPTION ="" GROUP ="UPD_INS" NAME ="MARK_REQ1" PICTURETEXT ="" PORTTYPE ="OUTPUT" PRECISION ="9" REF_FIELD ="MARK_REQ" SCALE ="0"/>
            <TRANSFORMFIELD DATATYPE ="integer" DEFAULTVALUE ="" DESCRIPTION ="Default port for Dynamic Lookup" GROUP ="DEFAULT1" NAME ="NewLookupRow2" PICTURETEXT ="" PORTTYPE ="OUTPUT" PRECISION ="10" REF_FIELD ="NewLookupRow" SCALE ="0"/>
            <TRANSFORMFIELD DATATYPE ="decimal" DEFAULTVALUE ="" DESCRIPTION ="" GROUP ="DEFAULT1" NAME ="COURSE_CODE2" PICTURETEXT ="" PORTTYPE ="OUTPUT" PRECISION ="10" REF_FIELD ="COURSE_CODE" SCALE ="0"/>
            <TRANSFORMFIELD DATATYPE ="string" DEFAULTVALUE ="" DESCRIPTION ="" GROUP ="DEFAULT1" NAME ="COURSE_NAME2" PICTURETEXT ="" PORTTYPE ="OUTPUT" PRECISION ="30" REF_FIELD ="COURSE_NAME" SCALE ="0"/>
            <TRANSFORMFIELD DATATYPE ="decimal" DEFAULTVALUE ="" DESCRIPTION ="" GROUP ="DEFAULT1" NAME ="DEPARTMENT_ID2" PICTURETEXT ="" PORTTYPE ="OUTPUT" PRECISION ="10" REF_FIELD ="DEPARTMENT_ID" SCALE ="0"/>
            <TRANSFORMFIELD DATATYPE ="string" DEFAULTVALUE ="" DESCRIPTION ="" GROUP ="DEFAULT1" NAME ="MARK_REQ2" PICTURETEXT ="" PORTTYPE ="OUTPUT" PRECISION ="9" REF_FIELD ="MARK_REQ" SCALE ="0"/>
            <TABLEATTRIBUTE NAME ="Tracing Level" VALUE ="Normal"/>
        </TRANSFORMATION>
        <TRANSFORMATION DESCRIPTION ="" NAME ="UPD_M_UAS_COURSE" OBJECTVERSION ="1" REUSABLE ="NO" TYPE ="Update Strategy" VERSIONNUMBER ="1">
            <TRANSFORMFIELD DATATYPE ="integer" DEFAULTVALUE ="" DESCRIPTION ="Default port for Dynamic Lookup" NAME ="NewLookupRow1" PICTURETEXT ="" PORTTYPE ="INPUT/OUTPUT" PRECISION ="10" SCALE ="0"/>
            <TRANSFORMFIELD DATATYPE ="decimal" DEFAULTVALUE ="" DESCRIPTION ="" NAME ="COURSE_CODE1" PICTURETEXT ="" PORTTYPE ="INPUT/OUTPUT" PRECISION ="10" SCALE ="0"/>
            <TRANSFORMFIELD DATATYPE ="string" DEFAULTVALUE ="" DESCRIPTION ="" NAME ="COURSE_NAME1" PICTURETEXT ="" PORTTYPE ="INPUT/OUTPUT" PRECISION ="30" SCALE ="0"/>
            <TRANSFORMFIELD DATATYPE ="decimal" DEFAULTVALUE ="" DESCRIPTION ="" NAME ="DEPARTMENT_ID1" PICTURETEXT ="" PORTTYPE ="INPUT/OUTPUT" PRECISION ="10" SCALE ="0"/>
            <TRANSFORMFIELD DATATYPE ="string" DEFAULTVALUE ="" DESCRIPTION ="" NAME ="MARK_REQ1" PICTURETEXT ="" PORTTYPE ="INPUT/OUTPUT" PRECISION ="9" SCALE ="0"/>
            <TABLEATTRIBUTE NAME ="Update Strategy Expression" VALUE ="IIF(NewLookupRow1=1,DD_INSERT,DD_UPDATE)"/>
            <TABLEATTRIBUTE NAME ="Forward Rejected Rows" VALUE ="YES"/>
            <TABLEATTRIBUTE NAME ="Tracing Level" VALUE ="Normal"/>
        </TRANSFORMATION>
        <TRANSFORMATION DESCRIPTION ="" NAME ="LKP_DEPARTMENT" OBJECTVERSION ="1" REUSABLE ="NO" TYPE ="Lookup Procedure" VERSIONNUMBER ="1">
            <TRANSFORMFIELD DATATYPE ="decimal" DEFAULTVALUE ="" DESCRIPTION ="" NAME ="DEPARTMENT_ID" PICTURETEXT ="" PORTTYPE ="LOOKUP/OUTPUT" PRECISION ="10" SCALE ="0"/>
            <TRANSFORMFIELD DATATYPE ="string" DEFAULTVALUE ="" DESCRIPTION ="" NAME ="DEPARTMENT_NAME" PICTURETEXT ="" PORTTYPE ="LOOKUP/OUTPUT" PRECISION ="50" SCALE ="0"/>
            <TRANSFORMFIELD DATATYPE ="decimal" DEFAULTVALUE ="" DESCRIPTION ="" NAME ="DEPARTMENT_NO" PICTURETEXT ="" PORTTYPE ="LOOKUP/OUTPUT" PRECISION ="9" SCALE ="0"/>
            <TRANSFORMFIELD DATATYPE ="string" DEFAULTVALUE ="" DESCRIPTION ="" NAME ="DEPARTMENT_PHONE" PICTURETEXT ="" PORTTYPE ="LOOKUP/OUTPUT" PRECISION ="12" SCALE ="0"/>
            <TRANSFORMFIELD DATATYPE ="string" DEFAULTVALUE ="" DESCRIPTION ="" NAME ="DEPARTMENT_HEAD" PICTURETEXT ="" PORTTYPE ="LOOKUP/OUTPUT" PRECISION ="30" SCALE ="0"/>
            <TRANSFORMFIELD DATATYPE ="decimal" DEFAULTVALUE ="" DESCRIPTION ="" NAME ="DEPARTMENT_NO_IN" PICTURETEXT ="" PORTTYPE ="INPUT/OUTPUT" PRECISION ="9" SCALE ="0"/>
            <TABLEATTRIBUTE NAME ="Lookup Sql Override" VALUE =""/>
            <TABLEATTRIBUTE NAME ="Lookup table name" VALUE ="CDW_UAS_D_DEPARTMENT"/>
            <TABLEATTRIBUTE NAME ="Lookup Source Filter" VALUE =""/>
            <TABLEATTRIBUTE NAME ="Lookup caching enabled" VALUE ="YES"/>
            <TABLEATTRIBUTE NAME ="Lookup policy on multiple match" VALUE ="Use Any Value"/>
            <TABLEATTRIBUTE NAME ="Lookup condition" VALUE ="DEPARTMENT_NO = DEPARTMENT_NO_IN"/>
            <TABLEATTRIBUTE NAME ="Connection Information" VALUE ="$Target"/>
            <TABLEATTRIBUTE NAME ="Source Type" VALUE ="Database"/>
            <TABLEATTRIBUTE NAME ="Recache if Stale" VALUE ="NO"/>
            <TABLEATTRIBUTE NAME ="Tracing Level" VALUE ="Normal"/>
            <TABLEATTRIBUTE NAME ="Lookup cache directory name" VALUE ="$PMCacheDir"/>
            <TABLEATTRIBUTE NAME ="Lookup cache initialize" VALUE ="NO"/>
            <TABLEATTRIBUTE NAME ="Lookup cache persistent" VALUE ="NO"/>
            <TABLEATTRIBUTE NAME ="Lookup Data Cache Size" VALUE ="Auto"/>
            <TABLEATTRIBUTE NAME ="Lookup Index Cache Size" VALUE ="Auto"/>
            <TABLEATTRIBUTE NAME ="Dynamic Lookup Cache" VALUE ="NO"/>
            <TABLEATTRIBUTE NAME ="Synchronize Dynamic Cache" VALUE ="NO"/>
            <TABLEATTRIBUTE NAME ="Output Old Value On Update" VALUE ="NO"/>
            <TABLEATTRIBUTE NAME ="Update Dynamic Cache Condition" VALUE ="TRUE"/>
            <TABLEATTRIBUTE NAME ="Cache File Name Prefix" VALUE =""/>
            <TABLEATTRIBUTE NAME ="Re-cache from lookup source" VALUE ="NO"/>
            <TABLEATTRIBUTE NAME ="Insert Else Update" VALUE ="NO"/>
            <TABLEATTRIBUTE NAME ="Update Else Insert" VALUE ="NO"/>
            <TABLEATTRIBUTE NAME ="Datetime Format" VALUE =""/>
            <TABLEATTRIBUTE NAME ="Thousand Separator" VALUE ="None"/>
            <TABLEATTRIBUTE NAME ="Decimal Separator" VALUE ="."/>
            <TABLEATTRIBUTE NAME ="Case Sensitive String Comparison" VALUE ="NO"/>
            <TABLEATTRIBUTE NAME ="Null ordering" VALUE ="Null Is Highest Value"/>
            <TABLEATTRIBUTE NAME ="Sorted Input" VALUE ="NO"/>
            <TABLEATTRIBUTE NAME ="Lookup source is static" VALUE ="NO"/>
            <TABLEATTRIBUTE NAME ="Pre-build lookup cache" VALUE ="Auto"/>
            <TABLEATTRIBUTE NAME ="Subsecond Precision" VALUE ="6"/>
        </TRANSFORMATION>
        <TRANSFORMATION DESCRIPTION ="" NAME ="EXP_COURSE" OBJECTVERSION ="1" REUSABLE ="NO" TYPE ="Expression" VERSIONNUMBER ="1">
            <TRANSFORMFIELD DATATYPE ="string" DEFAULTVALUE ="" DESCRIPTION ="" NAME ="COURSE_NAME" PICTURETEXT ="" PORTTYPE ="INPUT" PRECISION ="30" SCALE ="0"/>
            <TRANSFORMFIELD DATATYPE ="string" DEFAULTVALUE ="ERROR(&apos;transformation error&apos;)" DESCRIPTION ="" EXPRESSION ="RTRIM(COURSE_NAME)" EXPRESSIONTYPE ="GENERAL" NAME ="COURSE_NAME_O" PICTURETEXT ="" PORTTYPE ="OUTPUT" PRECISION ="30" SCALE ="0"/>
            <TRANSFORMFIELD DATATYPE ="string" DEFAULTVALUE ="" DESCRIPTION ="" EXPRESSION ="DEPARTMENT_NO" EXPRESSIONTYPE ="GENERAL" NAME ="DEPARTMENT_NO" PICTURETEXT ="" PORTTYPE ="INPUT/OUTPUT" PRECISION ="9" SCALE ="0"/>
            <TRANSFORMFIELD DATATYPE ="decimal" DEFAULTVALUE ="ERROR(&apos;transformation error&apos;)" DESCRIPTION ="" EXPRESSION ="TO_DECIMAL(DEPARTMENT_NO)" EXPRESSIONTYPE ="GENERAL" NAME ="DEPARTMENT_NO_O" PICTURETEXT ="" PORTTYPE ="OUTPUT" PRECISION ="9" SCALE ="0"/>
            <TRANSFORMFIELD DATATYPE ="string" DEFAULTVALUE ="" DESCRIPTION ="" NAME ="MARK_REQ" PICTURETEXT ="" PORTTYPE ="INPUT" PRECISION ="9" SCALE ="0"/>
            <TRANSFORMFIELD DATATYPE ="string" DEFAULTVALUE ="ERROR(&apos;transformation error&apos;)" DESCRIPTION ="" EXPRESSION ="RTRIM(MARK_REQ)" EXPRESSIONTYPE ="GENERAL" NAME ="MARK_REQ_O" PICTURETEXT ="" PORTTYPE ="OUTPUT" PRECISION ="9" SCALE ="0"/>
            <TABLEATTRIBUTE NAME ="Tracing Level" VALUE ="Normal"/>
        </TRANSFORMATION>
        <TRANSFORMATION DESCRIPTION ="" NAME ="SQ_CDW_UAS_COURSE" OBJECTVERSION ="1" REUSABLE ="NO" TYPE ="Source Qualifier" VERSIONNUMBER ="1">
            <TRANSFORMFIELD DATATYPE ="decimal" DEFAULTVALUE ="" DESCRIPTION ="" NAME ="COURSE_CODE" PICTURETEXT ="" PORTTYPE ="INPUT/OUTPUT" PRECISION ="10" SCALE ="10"/>
            <TRANSFORMFIELD DATATYPE ="string" DEFAULTVALUE ="" DESCRIPTION ="" NAME ="COURSE_NAME" PICTURETEXT ="" PORTTYPE ="INPUT/OUTPUT" PRECISION ="30" SCALE ="0"/>
            <TRANSFORMFIELD DATATYPE ="string" DEFAULTVALUE ="" DESCRIPTION ="" NAME ="DEPARTMENT_NO" PICTURETEXT ="" PORTTYPE ="INPUT/OUTPUT" PRECISION ="9" SCALE ="0"/>
            <TRANSFORMFIELD DATATYPE ="string" DEFAULTVALUE ="" DESCRIPTION ="" NAME ="MARK_REQ" PICTURETEXT ="" PORTTYPE ="INPUT/OUTPUT" PRECISION ="9" SCALE ="0"/>
            <TABLEATTRIBUTE NAME ="Sql Query" VALUE =""/>
            <TABLEATTRIBUTE NAME ="User Defined Join" VALUE =""/>
            <TABLEATTRIBUTE NAME ="Source Filter" VALUE =""/>
            <TABLEATTRIBUTE NAME ="Number Of Sorted Ports" VALUE ="0"/>
            <TABLEATTRIBUTE NAME ="Tracing Level" VALUE ="Normal"/>
            <TABLEATTRIBUTE NAME ="Select Distinct" VALUE ="NO"/>
            <TABLEATTRIBUTE NAME ="Is Partitionable" VALUE ="NO"/>
            <TABLEATTRIBUTE NAME ="Pre SQL" VALUE =""/>
            <TABLEATTRIBUTE NAME ="Post SQL" VALUE =""/>
            <TABLEATTRIBUTE NAME ="Output is deterministic" VALUE ="NO"/>
            <TABLEATTRIBUTE NAME ="Output is repeatable" VALUE ="Never"/>
        </TRANSFORMATION>
        <TRANSFORMATION DESCRIPTION ="" NAME ="LKP_COURSE_T" OBJECTVERSION ="1" REUSABLE ="NO" TYPE ="Lookup Procedure" VERSIONNUMBER ="1">
            <TRANSFORMFIELD DATATYPE ="integer" DEFAULTVALUE ="" DESCRIPTION ="Default port for Dynamic Lookup" NAME ="NewLookupRow" PICTURETEXT ="" PORTTYPE ="DYNLOOKUP/OUTPUT" PRECISION ="10" SCALE ="0"/>
            <TRANSFORMFIELD DATATYPE ="decimal" DEFAULTVALUE ="" DESCRIPTION ="" IGNORE_IN_COMPARE ="YES" IGNORE_NULL_INPUTS ="NO" NAME ="COURSE_CODE" PICTURETEXT ="" PORTTYPE ="LOOKUP/OUTPUT" PRECISION ="10" REF_FIELD ="COURSE_CODE_IN" SCALE ="0"/>
            <TRANSFORMFIELD DATATYPE ="string" DEFAULTVALUE ="" DESCRIPTION ="" IGNORE_IN_COMPARE ="NO" IGNORE_NULL_INPUTS ="NO" NAME ="COURSE_NAME" PICTURETEXT ="" PORTTYPE ="LOOKUP/OUTPUT" PRECISION ="30" REF_FIELD ="COURSE_NAME_IN" SCALE ="0"/>
            <TRANSFORMFIELD DATATYPE ="decimal" DEFAULTVALUE ="" DESCRIPTION ="" IGNORE_IN_COMPARE ="NO" IGNORE_NULL_INPUTS ="NO" NAME ="DEPARTMENT_ID" PICTURETEXT ="" PORTTYPE ="LOOKUP/OUTPUT" PRECISION ="10" REF_FIELD ="DEPARTMENT_ID_IN" SCALE ="0"/>
            <TRANSFORMFIELD DATATYPE ="string" DEFAULTVALUE ="" DESCRIPTION ="" IGNORE_IN_COMPARE ="NO" IGNORE_NULL_INPUTS ="NO" NAME ="MARK_REQ" PICTURETEXT ="" PORTTYPE ="LOOKUP/OUTPUT" PRECISION ="9" REF_FIELD ="MARK_REQ_IN" SCALE ="0"/>
            <TRANSFORMFIELD DATATYPE ="decimal" DEFAULTVALUE ="" DESCRIPTION ="" NAME ="COURSE_CODE_IN" PICTURETEXT ="" PORTTYPE ="INPUT" PRECISION ="10" SCALE ="10"/>
            <TRANSFORMFIELD DATATYPE ="string" DEFAULTVALUE ="" DESCRIPTION ="" NAME ="COURSE_NAME_IN" PICTURETEXT ="" PORTTYPE ="INPUT" PRECISION ="30" SCALE ="0"/>
            <TRANSFORMFIELD DATATYPE ="decimal" DEFAULTVALUE ="" DESCRIPTION ="" NAME ="DEPARTMENT_ID_IN" PICTURETEXT ="" PORTTYPE ="INPUT" PRECISION ="10" SCALE ="0"/>
            <TRANSFORMFIELD DATATYPE ="string" DEFAULTVALUE ="" DESCRIPTION ="" NAME ="MARK_REQ_IN" PICTURETEXT ="" PORTTYPE ="INPUT" PRECISION ="9" SCALE ="0"/>
            <TABLEATTRIBUTE NAME ="Lookup Sql Override" VALUE =""/>
            <TABLEATTRIBUTE NAME ="Lookup table name" VALUE ="CDW_SAPP_D_COURSE"/>
            <TABLEATTRIBUTE NAME ="Lookup Source Filter" VALUE =""/>
            <TABLEATTRIBUTE NAME ="Lookup caching enabled" VALUE ="YES"/>
            <TABLEATTRIBUTE NAME ="Lookup policy on multiple match" VALUE ="Report Error"/>
            <TABLEATTRIBUTE NAME ="Lookup condition" VALUE ="COURSE_CODE = COURSE_CODE_IN"/>
            <TABLEATTRIBUTE NAME ="Connection Information" VALUE ="$Target"/>
            <TABLEATTRIBUTE NAME ="Source Type" VALUE ="Database"/>
            <TABLEATTRIBUTE NAME ="Recache if Stale" VALUE ="NO"/>
            <TABLEATTRIBUTE NAME ="Tracing Level" VALUE ="Normal"/>
            <TABLEATTRIBUTE NAME ="Lookup cache directory name" VALUE ="$PMCacheDir"/>
            <TABLEATTRIBUTE NAME ="Lookup cache initialize" VALUE ="NO"/>
            <TABLEATTRIBUTE NAME ="Lookup cache persistent" VALUE ="NO"/>
            <TABLEATTRIBUTE NAME ="Lookup Data Cache Size" VALUE ="Auto"/>
            <TABLEATTRIBUTE NAME ="Lookup Index Cache Size" VALUE ="Auto"/>
            <TABLEATTRIBUTE NAME ="Dynamic Lookup Cache" VALUE ="YES"/>
            <TABLEATTRIBUTE NAME ="Synchronize Dynamic Cache" VALUE ="NO"/>
            <TABLEATTRIBUTE NAME ="Output Old Value On Update" VALUE ="NO"/>
            <TABLEATTRIBUTE NAME ="Update Dynamic Cache Condition" VALUE ="TRUE"/>
            <TABLEATTRIBUTE NAME ="Cache File Name Prefix" VALUE =""/>
            <TABLEATTRIBUTE NAME ="Re-cache from lookup source" VALUE ="NO"/>
            <TABLEATTRIBUTE NAME ="Insert Else Update" VALUE ="YES"/>
            <TABLEATTRIBUTE NAME ="Update Else Insert" VALUE ="NO"/>
            <TABLEATTRIBUTE NAME ="Datetime Format" VALUE =""/>
            <TABLEATTRIBUTE NAME ="Thousand Separator" VALUE ="None"/>
            <TABLEATTRIBUTE NAME ="Decimal Separator" VALUE ="."/>
            <TABLEATTRIBUTE NAME ="Case Sensitive String Comparison" VALUE ="NO"/>
            <TABLEATTRIBUTE NAME ="Null ordering" VALUE ="Null Is Highest Value"/>
            <TABLEATTRIBUTE NAME ="Sorted Input" VALUE ="NO"/>
            <TABLEATTRIBUTE NAME ="Lookup source is static" VALUE ="NO"/>
            <TABLEATTRIBUTE NAME ="Pre-build lookup cache" VALUE ="Auto"/>
            <TABLEATTRIBUTE NAME ="Subsecond Precision" VALUE ="6"/>
        </TRANSFORMATION>
        <INSTANCE DBDNAME ="FlatFile" DESCRIPTION ="" NAME ="CDW_UAS_COURSE" TRANSFORMATION_NAME ="CDW_UAS_COURSE" TRANSFORMATION_TYPE ="Source Definition" TYPE ="SOURCE"/>
        <INSTANCE DESCRIPTION ="" NAME ="RTR_U_I" REUSABLE ="NO" TRANSFORMATION_NAME ="RTR_U_I" TRANSFORMATION_TYPE ="Router" TYPE ="TRANSFORMATION"/>
        <INSTANCE DESCRIPTION ="" NAME ="UPD_M_UAS_COURSE" REUSABLE ="NO" TRANSFORMATION_NAME ="UPD_M_UAS_COURSE" TRANSFORMATION_TYPE ="Update Strategy" TYPE ="TRANSFORMATION"/>
        <INSTANCE DESCRIPTION ="" NAME ="LKP_DEPARTMENT" REUSABLE ="NO" TRANSFORMATION_NAME ="LKP_DEPARTMENT" TRANSFORMATION_TYPE ="Lookup Procedure" TYPE ="TRANSFORMATION"/>
        <INSTANCE DESCRIPTION ="" NAME ="EXP_COURSE" REUSABLE ="NO" TRANSFORMATION_NAME ="EXP_COURSE" TRANSFORMATION_TYPE ="Expression" TYPE ="TRANSFORMATION"/>
        <INSTANCE DESCRIPTION ="" NAME ="SQ_CDW_UAS_COURSE" REUSABLE ="NO" TRANSFORMATION_NAME ="SQ_CDW_UAS_COURSE" TRANSFORMATION_TYPE ="Source Qualifier" TYPE ="TRANSFORMATION">
            <ASSOCIATED_SOURCE_INSTANCE NAME ="CDW_UAS_COURSE"/>
        </INSTANCE>
        <INSTANCE DESCRIPTION ="" NAME ="LKP_COURSE_T" REUSABLE ="NO" TRANSFORMATION_NAME ="LKP_COURSE_T" TRANSFORMATION_TYPE ="Lookup Procedure" TYPE ="TRANSFORMATION"/>
        <INSTANCE DESCRIPTION ="" NAME ="CDW_SAPP_D_COURSE" TRANSFORMATION_NAME ="CDW_SAPP_D_COURSE" TRANSFORMATION_TYPE ="Target Definition" TYPE ="TARGET"/>
        <CONNECTOR FROMFIELD ="COURSE_CODE" FROMINSTANCE ="CDW_UAS_COURSE" FROMINSTANCETYPE ="Source Definition" TOFIELD ="COURSE_CODE" TOINSTANCE ="SQ_CDW_UAS_COURSE" TOINSTANCETYPE ="Source Qualifier"/>
        <CONNECTOR FROMFIELD ="COURSE_NAME" FROMINSTANCE ="CDW_UAS_COURSE" FROMINSTANCETYPE ="Source Definition" TOFIELD ="COURSE_NAME" TOINSTANCE ="SQ_CDW_UAS_COURSE" TOINSTANCETYPE ="Source Qualifier"/>
        <CONNECTOR FROMFIELD ="DEPARTMENT_NO" FROMINSTANCE ="CDW_UAS_COURSE" FROMINSTANCETYPE ="Source Definition" TOFIELD ="DEPARTMENT_NO" TOINSTANCE ="SQ_CDW_UAS_COURSE" TOINSTANCETYPE ="Source Qualifier"/>
        <CONNECTOR FROMFIELD ="MARK_REQ" FROMINSTANCE ="CDW_UAS_COURSE" FROMINSTANCETYPE ="Source Definition" TOFIELD ="MARK_REQ" TOINSTANCE ="SQ_CDW_UAS_COURSE" TOINSTANCETYPE ="Source Qualifier"/>
        <CONNECTOR FROMFIELD ="NewLookupRow" FROMINSTANCE ="LKP_COURSE_T" FROMINSTANCETYPE ="Lookup Procedure" TOFIELD ="NewLookupRow" TOINSTANCE ="RTR_U_I" TOINSTANCETYPE ="Router"/>
        <CONNECTOR FROMFIELD ="COURSE_CODE" FROMINSTANCE ="LKP_COURSE_T" FROMINSTANCETYPE ="Lookup Procedure" TOFIELD ="COURSE_CODE" TOINSTANCE ="RTR_U_I" TOINSTANCETYPE ="Router"/>
        <CONNECTOR FROMFIELD ="COURSE_NAME" FROMINSTANCE ="LKP_COURSE_T" FROMINSTANCETYPE ="Lookup Procedure" TOFIELD ="COURSE_NAME" TOINSTANCE ="RTR_U_I" TOINSTANCETYPE ="Router"/>
        <CONNECTOR FROMFIELD ="DEPARTMENT_ID" FROMINSTANCE ="LKP_COURSE_T" FROMINSTANCETYPE ="Lookup Procedure" TOFIELD ="DEPARTMENT_ID" TOINSTANCE ="RTR_U_I" TOINSTANCETYPE ="Router"/>
        <CONNECTOR FROMFIELD ="MARK_REQ" FROMINSTANCE ="LKP_COURSE_T" FROMINSTANCETYPE ="Lookup Procedure" TOFIELD ="MARK_REQ" TOINSTANCE ="RTR_U_I" TOINSTANCETYPE ="Router"/>
        <CONNECTOR FROMFIELD ="NewLookupRow1" FROMINSTANCE ="RTR_U_I" FROMINSTANCETYPE ="Router" TOFIELD ="NewLookupRow1" TOINSTANCE ="UPD_M_UAS_COURSE" TOINSTANCETYPE ="Update Strategy"/>
        <CONNECTOR FROMFIELD ="COURSE_CODE1" FROMINSTANCE ="RTR_U_I" FROMINSTANCETYPE ="Router" TOFIELD ="COURSE_CODE1" TOINSTANCE ="UPD_M_UAS_COURSE" TOINSTANCETYPE ="Update Strategy"/>
        <CONNECTOR FROMFIELD ="COURSE_NAME1" FROMINSTANCE ="RTR_U_I" FROMINSTANCETYPE ="Router" TOFIELD ="COURSE_NAME1" TOINSTANCE ="UPD_M_UAS_COURSE" TOINSTANCETYPE ="Update Strategy"/>
        <CONNECTOR FROMFIELD ="DEPARTMENT_ID1" FROMINSTANCE ="RTR_U_I" FROMINSTANCETYPE ="Router" TOFIELD ="DEPARTMENT_ID1" TOINSTANCE ="UPD_M_UAS_COURSE" TOINSTANCETYPE ="Update Strategy"/>
        <CONNECTOR FROMFIELD ="MARK_REQ1" FROMINSTANCE ="RTR_U_I" FROMINSTANCETYPE ="Router" TOFIELD ="MARK_REQ1" TOINSTANCE ="UPD_M_UAS_COURSE" TOINSTANCETYPE ="Update Strategy"/>
        <CONNECTOR FROMFIELD ="COURSE_CODE1" FROMINSTANCE ="UPD_M_UAS_COURSE" FROMINSTANCETYPE ="Update Strategy" TOFIELD ="COURSE_CODE" TOINSTANCE ="CDW_SAPP_D_COURSE" TOINSTANCETYPE ="Target Definition"/>
        <CONNECTOR FROMFIELD ="COURSE_NAME1" FROMINSTANCE ="UPD_M_UAS_COURSE" FROMINSTANCETYPE ="Update Strategy" TOFIELD ="COURSE_NAME" TOINSTANCE ="CDW_SAPP_D_COURSE" TOINSTANCETYPE ="Target Definition"/>
        <CONNECTOR FROMFIELD ="DEPARTMENT_ID1" FROMINSTANCE ="UPD_M_UAS_COURSE" FROMINSTANCETYPE ="Update Strategy" TOFIELD ="DEPARTMENT_ID" TOINSTANCE ="CDW_SAPP_D_COURSE" TOINSTANCETYPE ="Target Definition"/>
        <CONNECTOR FROMFIELD ="MARK_REQ1" FROMINSTANCE ="UPD_M_UAS_COURSE" FROMINSTANCETYPE ="Update Strategy" TOFIELD ="MARK_REQ" TOINSTANCE ="CDW_SAPP_D_COURSE" TOINSTANCETYPE ="Target Definition"/>
        <CONNECTOR FROMFIELD ="DEPARTMENT_NO_O" FROMINSTANCE ="EXP_COURSE" FROMINSTANCETYPE ="Expression" TOFIELD ="DEPARTMENT_NO_IN" TOINSTANCE ="LKP_DEPARTMENT" TOINSTANCETYPE ="Lookup Procedure"/>
        <CONNECTOR FROMFIELD ="DEPARTMENT_ID" FROMINSTANCE ="LKP_DEPARTMENT" FROMINSTANCETYPE ="Lookup Procedure" TOFIELD ="DEPARTMENT_ID_IN" TOINSTANCE ="LKP_COURSE_T" TOINSTANCETYPE ="Lookup Procedure"/>
        <CONNECTOR FROMFIELD ="DEPARTMENT_NO" FROMINSTANCE ="SQ_CDW_UAS_COURSE" FROMINSTANCETYPE ="Source Qualifier" TOFIELD ="DEPARTMENT_NO" TOINSTANCE ="EXP_COURSE" TOINSTANCETYPE ="Expression"/>
        <CONNECTOR FROMFIELD ="COURSE_NAME" FROMINSTANCE ="SQ_CDW_UAS_COURSE" FROMINSTANCETYPE ="Source Qualifier" TOFIELD ="COURSE_NAME" TOINSTANCE ="EXP_COURSE" TOINSTANCETYPE ="Expression"/>
        <CONNECTOR FROMFIELD ="MARK_REQ" FROMINSTANCE ="SQ_CDW_UAS_COURSE" FROMINSTANCETYPE ="Source Qualifier" TOFIELD ="MARK_REQ" TOINSTANCE ="EXP_COURSE" TOINSTANCETYPE ="Expression"/>
        <CONNECTOR FROMFIELD ="COURSE_NAME_O" FROMINSTANCE ="EXP_COURSE" FROMINSTANCETYPE ="Expression" TOFIELD ="COURSE_NAME_IN" TOINSTANCE ="LKP_COURSE_T" TOINSTANCETYPE ="Lookup Procedure"/>
        <CONNECTOR FROMFIELD ="MARK_REQ_O" FROMINSTANCE ="EXP_COURSE" FROMINSTANCETYPE ="Expression" TOFIELD ="MARK_REQ_IN" TOINSTANCE ="LKP_COURSE_T" TOINSTANCETYPE ="Lookup Procedure"/>
        <CONNECTOR FROMFIELD ="COURSE_CODE" FROMINSTANCE ="SQ_CDW_UAS_COURSE" FROMINSTANCETYPE ="Source Qualifier" TOFIELD ="COURSE_CODE_IN" TOINSTANCE ="LKP_COURSE_T" TOINSTANCETYPE ="Lookup Procedure"/>
        <TARGETLOADORDER ORDER ="1" TARGETINSTANCE ="CDW_SAPP_D_COURSE"/>
        <ERPINFO/>
    </MAPPING>
</FOLDER>
</REPOSITORY>
</POWERMART>